odoo/addons/pos_sale_pos_event_sale_session/README.rst
odoo/addons/pos_sale_pos_event_sale_session/__init__.py
odoo/addons/pos_sale_pos_event_sale_session/__manifest__.py
odoo/addons/pos_sale_pos_event_sale_session/i18n/es.po
odoo/addons/pos_sale_pos_event_sale_session/i18n/it.po
odoo/addons/pos_sale_pos_event_sale_session/i18n/pos_sale_pos_event_sale_session.pot
odoo/addons/pos_sale_pos_event_sale_session/models/__init__.py
odoo/addons/pos_sale_pos_event_sale_session/models/sale_order_line.py
odoo/addons/pos_sale_pos_event_sale_session/readme/CONTRIBUTORS.rst
odoo/addons/pos_sale_pos_event_sale_session/readme/DESCRIPTION.rst
odoo/addons/pos_sale_pos_event_sale_session/static/description/icon.png
odoo/addons/pos_sale_pos_event_sale_session/static/description/index.html
odoo/addons/pos_sale_pos_event_sale_session/static/src/js/SaleOrderManagementScreen.js
odoo/addons/pos_sale_pos_event_sale_session/static/src/js/models.js
odoo_addon_pos_sale_pos_event_sale_session-15.0.1.0.0.10.dist-info/METADATA
odoo_addon_pos_sale_pos_event_sale_session-15.0.1.0.0.10.dist-info/WHEEL
odoo_addon_pos_sale_pos_event_sale_session-15.0.1.0.0.10.dist-info/top_level.txt
odoo_addon_pos_sale_pos_event_sale_session-15.0.1.0.0.10.dist-info/RECORD
